<?xml version="1.0" encoding="utf-8" ?>
	<Tests>
	 <Test>
        <ReqDef>..\AssetsDev\SAMRP2_SAMSF\AutoDowntime-Read.xml</ReqDef>
        <Output>..\Exports\AutoDowntime-Response.xml</Output>
		<Expected>..\AssetsDev\SAMRP2_SAMSF\AutoDowntime-Expected.xml</Expected>
    </Test>
	 <Test>
        <ReqDef>..\AssetsDev\SAMRP2_SAMSF\CalendarDateTime-Read.xml</ReqDef>
        <Output>..\Exports\CalendarDateTime-Response.xml</Output>
		<Expected>..\AssetsDev\SAMRP2_SAMSF\CalendarDateTime-Expected.xml</Expected>
    </Test>
	 <Test>
        <ReqDef>..\AssetsDev\SAMRP2_SAMSF\CrankSwitchPosition-Read.xml</ReqDef>
        <Output>..\Exports\CrankSwitchPosition-Response.xml</Output>
		<Expected>..\AssetsDev\SAMRP2_SAMSF\CrankSwitchPosition-Expected.xml</Expected>
    </Test>
	 <Test>
        <ReqDef>..\AssetsDev\SAMRP2_SAMSF\DateTimeParameters-Read.xml</ReqDef>
        <Output>..\Exports\DateTimeParameters-Response.xml</Output>
		<Expected>..\AssetsDev\SAMRP2_SAMSF\DateTimeParameters-Expected.xml</Expected>
    </Test>
	 <Test>
        <ReqDef>..\AssetsDev\SAMRP2_SAMSF\LinearPumpingUnitCorneringSupport-Read.xml</ReqDef>
        <Output>..\Exports\LinearPumpingUnitCorneringSupport-Response.xml</Output>
		<Expected>..\AssetsDev\SAMRP2_SAMSF\LinearPumpingUnitCorneringSupport-Expected.xml</Expected>
    </Test>
	 <Test>
        <ReqDef>..\AssetsDev\SAMRP2_SAMSF\LoadTransducer-Read.xml</ReqDef>
        <Output>..\Exports\LoadTransducer-Response.xml</Output>
		<Expected>..\AssetsDev\SAMRP2_SAMSF\LoadTransducer-Expected.xml</Expected>
    </Test>
	<Test>
        <ReqDef>..\AssetsDev\SAMRP2_SAMSF\PhysicalDigitalOutputs-Read.xml</ReqDef>
        <Output>..\Exports\PhysicalDigitalOutputs-Response.xml</Output>
		<Expected>..\AssetsDev\SAMRP2_SAMSF\PhysicalDigitalOutputs-Expected.xml</Expected>
    </Test>
	<Test>
        <ReqDef>..\AssetsDev\SAMRP2_SAMSF\RPCStatus-Read.xml</ReqDef>
        <Output>..\Exports\RPCStatus-Response.xml</Output>
		<Expected>..\AssetsDev\SAMRP2_SAMSF\RPCStatus-Expected.xml</Expected>
    </Test>
	<Test>
        <ReqDef>..\AssetsDev\SAMRP2_SAMSF\SAMDownholeConfig-Read.xml</ReqDef>
        <Output>..\Exports\SAMDownholeConfig-Response.xml</Output>
		<Expected>..\AssetsDev\SAMRP2_SAMSF\SAMDownholeConfig-Expected.xml</Expected>
    </Test>
    <Test>
        <ReqDef>..\AssetsDev\SAMRP2_SAMSF\SAMRP2AGAParms-Read.xml</ReqDef>
        <Output>..\Exports\SAMRP2AGAParms-Response.xml</Output>
		<Expected>..\AssetsDev\SAMRP2_SAMSF\SAMRP2AGAParms-Expected.xml</Expected>
    </Test>
	<Test>
        <ReqDef>..\AssetsDev\SAMRP2_SAMSF\SAMRP2AGAStatus-Read.xml</ReqDef>
        <Output>..\Exports\SAMRP2AGAStatus-Response.xml</Output>
		<Expected>..\AssetsDev\SAMRP2_SAMSF\SAMRP2AGAStatus-Expected.xml</Expected>
    </Test>   
	<Test>
        <ReqDef>..\AssetsDev\SAMRP2_SAMSF\SAMRP2AlarmRegs1-4-Read.xml</ReqDef>
        <Output>..\Exports\SAMRP2AlarmRegs1-4-Response.xml</Output>
		<Expected>..\AssetsDev\SAMRP2_SAMSF\SAMRP2AlarmRegs1-4-Expected.xml</Expected>
    </Test>   
	<Test>
        <ReqDef>..\AssetsDev\SAMRP2_SAMSF\SAMRP2AlarmsRegs5-8-Read.xml</ReqDef>
        <Output>..\Exports\SAMRP2AlarmsRegs5-8-Response.xml</Output>
		<Expected>..\AssetsDev\SAMRP2_SAMSF\SAMRP2AlarmsRegs5-8-Expected.xml</Expected>
    </Test>   
	<Test>
        <ReqDef>..\AssetsDev\SAMRP2_SAMSF\SAMRP2AlarmTracking-Read.xml</ReqDef>
        <Output>..\Exports\SAMRP2AlarmTracking-Response.xml</Output>
		<Expected>..\AssetsDev\SAMRP2_SAMSF\SAMRP2AlarmTracking-Expected.xml</Expected>
    </Test>  
	<Test>
        <ReqDef>..\AssetsDev\SAMRP2_SAMSF\SAMRP2AlarmTrackStatus-Read.xml</ReqDef>
        <Output>..\Exports\SAMRP2AlarmTrackStatus-Response.xml</Output>
		<Expected>..\AssetsDev\SAMRP2_SAMSF\SAMRP2AlarmTrackStatus-Expected.xml</Expected>
    </Test>   	
 	<Test>
        <ReqDef>..\AssetsDev\SAMRP2_SAMSF\SAMRP2AnalogInPut1-6-Read.xml</ReqDef>
        <Output>..\Exports\SAMRP2AnalogInPut1-6-Response.xml</Output>
		<Expected>..\AssetsDev\SAMRP2_SAMSF\SAMRP2AnalogInPut1-6-Expected.xml</Expected>
    </Test>   	
	<Test>
        <ReqDef>..\AssetsDev\SAMRP2_SAMSF\SAMRP2AnalogInPut7-12-Read.xml</ReqDef>
        <Output>..\Exports\SAMRP2AnalogInPut7-12-Response.xml</Output>
		<Expected>..\AssetsDev\SAMRP2_SAMSF\SAMRP2AnalogInPut7-12-Expected.xml</Expected>
    </Test>   	
	<Test>
        <ReqDef>..\AssetsDev\SAMRP2_SAMSF\SAMRP2AnalogInPut13-18-Read.xml</ReqDef>
        <Output>..\Exports\SAMRP2AnalogInPut13-18-Response.xml</Output>
		<Expected>..\AssetsDev\SAMRP2_SAMSF\SAMRP2AnalogInPut13-18-Expected.xml</Expected>
    </Test>   	
	<Test>
        <ReqDef>..\AssetsDev\SAMRP2_SAMSF\SAMRP2AnalogInPut19-24-Read.xml</ReqDef>
        <Output>..\Exports\SAMRP2AnalogInPut19-24-Response.xml</Output>
		<Expected>..\AssetsDev\SAMRP2_SAMSF\SAMRP2AnalogInPut19-24-Expected.xml</Expected>
    </Test>   	
	<Test>
        <ReqDef>..\AssetsDev\SAMRP2_SAMSF\SAMRP2AnalogInPut25-30-Read.xml</ReqDef>
        <Output>..\Exports\SAMRP2AnalogInPut25-30-Response.xml</Output>
		<Expected>..\AssetsDev\SAMRP2_SAMSF\SAMRP2AnalogInPut25-30-Expected.xml</Expected>
    </Test>   	
	<Test>
        <ReqDef>..\AssetsDev\SAMRP2_SAMSF\SAMRP2AnalogInPut31-32-Read.xml</ReqDef>
        <Output>..\Exports\SAMRP2AnalogInPut31-32-Response.xml</Output>
		<Expected>..\AssetsDev\SAMRP2_SAMSF\SAMRP2AnalogInPut31-32-Expected.xml</Expected>
    </Test>   	
	<Test>
        <ReqDef>..\AssetsDev\SAMRP2_SAMSF\SAMRP2AnalogOutput1-8-Read.xml</ReqDef>
        <Output>..\Exports\SAMRP2AnalogOutput1-8-Response.xml</Output>
		<Expected>..\AssetsDev\SAMRP2_SAMSF\SAMRP2AnalogOutput1-8-Expected.xml</Expected>
    </Test>   	
	<Test>
        <ReqDef>..\AssetsDev\SAMRP2_SAMSF\SAMRP2ContrlParms-Read.xml</ReqDef>
        <Output>..\Exports\SAMRP2ContrlParms-Response.xml</Output>
		<Expected>..\AssetsDev\SAMRP2_SAMSF\SAMRP2ContrlParms-Expected.xml</Expected>
    </Test>   	
	<Test>
        <ReqDef>..\AssetsDev\SAMRP2_SAMSF\SAMRP2ControllerInfo-Read.xml</ReqDef>
        <Output>..\Exports\SAMRP2ControllerInfo-Response.xml</Output>
		<Expected>..\AssetsDev\SAMRP2_SAMSF\SAMRP2ControllerInfo-Expected.xml</Expected>
    </Test>   	
	<Test>
        <ReqDef>..\AssetsDev\SAMRP2_SAMSF\SAMRP2DigitalConfig1-16-Read.xml</ReqDef>
        <Output>..\Exports\SAMRP2DigitalConfig1-16-Response.xml</Output>
		<Expected>..\AssetsDev\SAMRP2_SAMSF\SAMRP2DigitalConfig1-16-Expected.xml</Expected>
    </Test>   	
	<Test>
        <ReqDef>..\AssetsDev\SAMRP2_SAMSF\SAMRP2DigitalConfig17-32-Read.xml</ReqDef>
        <Output>..\Exports\SAMRP2DigitalConfig17-32-Response.xml</Output>
		<Expected>..\AssetsDev\SAMRP2_SAMSF\SAMRP2DigitalConfig17-32-Expected.xml</Expected>
    </Test>   	
	<Test>
        <ReqDef>..\AssetsDev\SAMRP2_SAMSF\SAMRP2DigitalConfig33-48-Read.xml</ReqDef>
        <Output>..\Exports\SAMRP2DigitalConfig33-48-Response.xml</Output>
		<Expected>..\AssetsDev\SAMRP2_SAMSF\SAMRP2DigitalConfig33-48-Expected.xml</Expected>
    </Test>   	
	<Test>
        <ReqDef>..\AssetsDev\SAMRP2_SAMSF\SAMRP2DigitalConfig49-64-Read.xml</ReqDef>
        <Output>..\Exports\SAMRP2DigitalConfig49-64-Response.xml</Output>
		<Expected>..\AssetsDev\SAMRP2_SAMSF\SAMRP2DigitalConfig49-64-Expected.xml</Expected>
    </Test>   	
	<Test>
        <ReqDef>..\AssetsDev\SAMRP2_SAMSF\SAMRP2Downhole-Read.xml</ReqDef>
        <Output>..\Exports\SAMRP2Downhole-Response.xml</Output>
		<Expected>..\AssetsDev\SAMRP2_SAMSF\SAMRP2Downhole-Expected.xml</Expected>
    </Test>   	
	<Test>
        <ReqDef>..\AssetsDev\SAMRP2_SAMSF\SAMRP2enable-violation-flag-Read.xml</ReqDef>
        <Output>..\Exports\SAMRP2enable-violation-flag-Response.xml</Output>
		<Expected>..\AssetsDev\SAMRP2_SAMSF\SAMRP2enable-violation-flag-Expected.xml</Expected>
    </Test>   	
	<Test>
        <ReqDef>..\AssetsDev\SAMRP2_SAMSF\SAMRP2LFKA1DriveFaults-Read.xml</ReqDef>
        <Output>..\Exports\SAMRP2LFKA1DriveFaults-Response.xml</Output>
		<Expected>..\AssetsDev\SAMRP2_SAMSF\SAMRP2LFKA1DriveFaults-Expected.xml</Expected>
    </Test>   	
	<Test>
        <ReqDef>..\AssetsDev\SAMRP2_SAMSF\SAMRP2LinearPump-Read.xml</ReqDef>
        <Output>..\Exports\SAMRP2LinearPump-Response.xml</Output>
		<Expected>..\AssetsDev\SAMRP2_SAMSF\SAMRP2LinearPump-Expected.xml</Expected>
    </Test>   	
	<Test>
        <ReqDef>..\AssetsDev\SAMRP2_SAMSF\SAMRP2LoadParms-Read.xml</ReqDef>
        <Output>..\Exports\SAMRP2LoadParms-Response.xml</Output>
		<Expected>..\AssetsDev\SAMRP2_SAMSF\SAMRP2LoadParms-Expected.xml</Expected>
    </Test>   	
	<Test>
        <ReqDef>..\AssetsDev\SAMRP2_SAMSF\SAMRP2LoadStatus-Read.xml</ReqDef>
        <Output>..\Exports\SAMRP2LoadStatus-Response.xml</Output>
		<Expected>..\AssetsDev\SAMRP2_SAMSF\SAMRP2LoadStatus-Expected.xml</Expected>
    </Test>   	
	<Test>
        <ReqDef>..\AssetsDev\SAMRP2_SAMSF\SAMRP2MotorPowerConf-Read.xml</ReqDef>
        <Output>..\Exports\SAMRP2MotorPowerConf-Response.xml</Output>
		<Expected>..\AssetsDev\SAMRP2_SAMSF\SAMRP2MotorPowerConf-Expected.xml</Expected>
    </Test>   	
	<Test>
        <ReqDef>..\AssetsDev\SAMRP2_SAMSF\SAMRP2PEMParms-Read.xml</ReqDef>
        <Output>..\Exports\SAMRP2PEMParms-Response.xml</Output>
		<Expected>..\AssetsDev\SAMRP2_SAMSF\SAMRP2PEMParms-Expected.xml</Expected>
    </Test>   	
	<Test>
        <ReqDef>..\AssetsDev\SAMRP2_SAMSF\SAMRP2PIPRegisters-Read.xml</ReqDef>
        <Output>..\Exports\SAMRP2PIPRegisters-Response.xml</Output>
		<Expected>..\AssetsDev\SAMRP2_SAMSF\SAMRP2PIPRegisters-Expected.xml</Expected>
    </Test>   	
	<Test>
        <ReqDef>..\AssetsDev\SAMRP2_SAMSF\SAMRP2POCStatus-Read.xml</ReqDef>
        <Output>..\Exports\SAMRP2POCStatus-Response.xml</Output>
		<Expected>..\AssetsDev\SAMRP2_SAMSF\SAMRP2POCStatus-Expected.xml</Expected>
    </Test>   	
	<Test>
        <ReqDef>..\AssetsDev\SAMRP2_SAMSF\SAMRP2PumpUnitDims-Read.xml</ReqDef>
        <Output>..\Exports\SAMRP2PumpUnitDims-Response.xml</Output>
		<Expected>..\AssetsDev\SAMRP2_SAMSF\SAMRP2PumpUnitDims-Expected.xml</Expected>
    </Test>   	
	<Test>
        <ReqDef>..\AssetsDev\SAMRP2_SAMSF\SAMRP2RodTapers-Read.xml</ReqDef>
        <Output>..\Exports\SAMRP2RodTapers-Response.xml</Output>
		<Expected>..\AssetsDev\SAMRP2_SAMSF\SAMRP2RodTapers-Expected.xml</Expected>
    </Test>   	
	
	<Test>
        <ReqDef>..\AssetsDev\SAMRP2_SAMSF\SAMRP2SPMPumpFillage-Read.xml</ReqDef>
        <Output>..\Exports\SAMRP2SPMPumpFillage-Response.xml</Output>
		<Expected>..\AssetsDev\SAMRP2_SAMSF\SAMRP2SPMPumpFillage-Expected.xml</Expected>
    </Test>   	
	<Test>
        <ReqDef>..\AssetsDev\SAMRP2_SAMSF\SAMRP2TRANSDRParms-Read.xml</ReqDef>
        <Output>..\Exports\SAMRP2TRANSDRParms-Response.xml</Output>
		<Expected>..\AssetsDev\SAMRP2_SAMSF\SAMRP2TRANSDRParms-Expected.xml</Expected>
    </Test>   	
	<Test>
        <ReqDef>..\AssetsDev\SAMRP2_SAMSF\SAMRP2TransducerStatus-Read.xml</ReqDef>
        <Output>..\Exports\SAMRP2TransducerStatus-Response.xml</Output>
		<Expected>..\AssetsDev\SAMRP2_SAMSF\SAMRP2TransducerStatus-Expected.xml</Expected>
    </Test>   	
	<Test>
        <ReqDef>..\AssetsDev\SAMRP2_SAMSF\SAMRP2Values-Read.xml</ReqDef>
        <Output>..\Exports\SAMRP2Values-Response.xml</Output>
		<Expected>..\AssetsDev\SAMRP2_SAMSF\SAMRP2Values-Expected.xml</Expected>
    </Test>   	
	<Test>
        <ReqDef>..\AssetsDev\SAMRP2_SAMSF\SAMRP2ValveCheck-Read.xml</ReqDef>
        <Output>..\Exports\SAMRP2ValveCheck-Response.xml</Output>
		<Expected>..\AssetsDev\SAMRP2_SAMSF\SAMRP2ValveCheck-Expected.xml</Expected>
    </Test>   	
	<Test>
        <ReqDef>..\AssetsDev\SAMRP2_SAMSF\SAMRP2ViolationConfig-Read.xml</ReqDef>
        <Output>..\Exports\SAMRP2ViolationConfig-Response.xml</Output>
		<Expected>..\AssetsDev\SAMRP2_SAMSF\SAMRP2ViolationConfig-Expected.xml</Expected>
    </Test>   	
	<Test>
        <ReqDef>..\AssetsDev\SAMRP2_SAMSF\SAMRP2Violations-Read.xml</ReqDef>
        <Output>..\Exports\SAMRP2Violations-Response.xml</Output>
		<Expected>..\AssetsDev\SAMRP2_SAMSF\SAMRP2Violations-Expected.xml</Expected>
    </Test>   	
	<Test>
        <ReqDef>..\AssetsDev\SAMRP2_SAMSF\SAMRP2WorkingValveCheck-Read.xml</ReqDef>
        <Output>..\Exports\SAMRP2WorkingValveCheck-Response.xml</Output>
		<Expected>..\AssetsDev\SAMRP2_SAMSF\SAMRP2WorkingValveCheck-Expected.xml</Expected>
    </Test>   	
	
</Tests>
